trytond/modules/cashbook_report/README.rst
trytond/modules/cashbook_report/__init__.py
trytond/modules/cashbook_report/colors.py
trytond/modules/cashbook_report/currency.py
trytond/modules/cashbook_report/evaluation.py
trytond/modules/cashbook_report/evaluation.xml
trytond/modules/cashbook_report/evaluation_context.py
trytond/modules/cashbook_report/evaluation_context.xml
trytond/modules/cashbook_report/evaluation_wizard.py
trytond/modules/cashbook_report/evaluation_wizard.xml
trytond/modules/cashbook_report/icon.xml
trytond/modules/cashbook_report/investment.py
trytond/modules/cashbook_report/ir.py
trytond/modules/cashbook_report/ir.xml
trytond/modules/cashbook_report/line.py
trytond/modules/cashbook_report/line.xml
trytond/modules/cashbook_report/menu.xml
trytond/modules/cashbook_report/message.xml
trytond/modules/cashbook_report/templates.py
trytond/modules/cashbook_report/tryton.cfg
trytond/modules/cashbook_report/versiondep.txt
trytond/modules/cashbook_report/icon/piechart.svg
trytond/modules/cashbook_report/locale/de.po
trytond/modules/cashbook_report/locale/en.po
trytond/modules/cashbook_report/tests/__init__.py
trytond/modules/cashbook_report/tests/test_report.py
trytond/modules/cashbook_report/view/evalline_form.xml
trytond/modules/cashbook_report/view/evalline_graph.xml
trytond/modules/cashbook_report/view/evalline_list.xml
trytond/modules/cashbook_report/view/evaluation_context_form.xml
trytond/modules/cashbook_report/view/evaluation_form.xml
trytond/modules/cashbook_report/view/evaluation_list.xml
mds_cashbook_report-7.0.11.dist-info/LICENSE
mds_cashbook_report-7.0.11.dist-info/METADATA
mds_cashbook_report-7.0.11.dist-info/WHEEL
mds_cashbook_report-7.0.11.dist-info/entry_points.txt
mds_cashbook_report-7.0.11.dist-info/top_level.txt
mds_cashbook_report-7.0.11.dist-info/RECORD
